odoo/addons/ssi_general_audit_worksheet_inherent_risk/README.rst
odoo/addons/ssi_general_audit_worksheet_inherent_risk/__init__.py
odoo/addons/ssi_general_audit_worksheet_inherent_risk/__manifest__.py
odoo/addons/ssi_general_audit_worksheet_inherent_risk/data/general_audit_worksheet_type_data.xml
odoo/addons/ssi_general_audit_worksheet_inherent_risk/data/approval_template/general_audit_ws_a418d89.xml
odoo/addons/ssi_general_audit_worksheet_inherent_risk/data/approval_template/general_audit_ws_c16abd7.xml
odoo/addons/ssi_general_audit_worksheet_inherent_risk/data/ir_sequence/general_audit_ws_a418d89.xml
odoo/addons/ssi_general_audit_worksheet_inherent_risk/data/ir_sequence/general_audit_ws_c16abd7.xml
odoo/addons/ssi_general_audit_worksheet_inherent_risk/data/policy_template/general_audit_ws_a418d89.xml
odoo/addons/ssi_general_audit_worksheet_inherent_risk/data/policy_template/general_audit_ws_c16abd7.xml
odoo/addons/ssi_general_audit_worksheet_inherent_risk/data/sequence_template/general_audit_ws_a418d89.xml
odoo/addons/ssi_general_audit_worksheet_inherent_risk/data/sequence_template/general_audit_ws_c16abd7.xml
odoo/addons/ssi_general_audit_worksheet_inherent_risk/models/__init__.py
odoo/addons/ssi_general_audit_worksheet_inherent_risk/models/general_audit.py
odoo/addons/ssi_general_audit_worksheet_inherent_risk/models/general_audit_inherent_risk_factor.py
odoo/addons/ssi_general_audit_worksheet_inherent_risk/models/general_audit_standard_detail.py
odoo/addons/ssi_general_audit_worksheet_inherent_risk/models/general_audit_ws_a418d89.py
odoo/addons/ssi_general_audit_worksheet_inherent_risk/models/general_audit_ws_a418d89_detail.py
odoo/addons/ssi_general_audit_worksheet_inherent_risk/models/general_audit_ws_c16abd7.py
odoo/addons/ssi_general_audit_worksheet_inherent_risk/security/ir.model.access.csv
odoo/addons/ssi_general_audit_worksheet_inherent_risk/security/ir_module_category_data.xml
odoo14_addon_ssi_general_audit_worksheet_inherent_risk-14.0.2.1.0.dist-info/METADATA
odoo14_addon_ssi_general_audit_worksheet_inherent_risk-14.0.2.1.0.dist-info/WHEEL
odoo14_addon_ssi_general_audit_worksheet_inherent_risk-14.0.2.1.0.dist-info/top_level.txt
odoo14_addon_ssi_general_audit_worksheet_inherent_risk-14.0.2.1.0.dist-info/RECORD
